chain_ensembles/__init__.py
chain_ensembles/chain_sim.py
chain_ensembles/hf_link.py
chain_ensembles/llm_chain.py
chain_ensembles/openai_link.py
chain_ensembles/prompters/__init__.py
chain_ensembles/prompters/ibc_prompter.py
chain_ensembles/prompters/misinfo_prompter.py
chain_ensembles/prompters/prompter.py
chain_ensembles/prompters/stance_prompter.py
chain_ensembles-0.1.2.dist-info/METADATA
chain_ensembles-0.1.2.dist-info/WHEEL
chain_ensembles-0.1.2.dist-info/licenses/LICENSE
chain_ensembles-0.1.2.dist-info/RECORD
