Metadata-Version: 2.3
Name: chain-ensembles
Version: 0.1.2
Summary: A python package for LLM Chain Ensembles!
Author-email: Nico Manzonelli <nicomanzonelli@gmail.com>
Requires-Python: >=3.12.0
Requires-Dist: accelerate>=1.2.0
Requires-Dist: chromadb>=0.5.20
Requires-Dist: huggingface-hub>=0.26.5
Requires-Dist: langchain-community>=0.3.8
Requires-Dist: langchain-openai>=0.2.9
Requires-Dist: langchain>=0.3.8
Requires-Dist: optimum-quanto>=0.2.6
Requires-Dist: pandas>=2.2.3
Requires-Dist: scikit-learn>=1.5.2
Requires-Dist: torch>=2.5.1
Requires-Dist: tqdm>=4.67.1
Requires-Dist: transformers>=4.47.0
